finspector/__init__.py
finspector/_version.py
finspector/finspector.py
finspector/labextension/package.json
finspector/labextension/static/154.77b0c11fea510ea9cf19.js
finspector/labextension/static/261.ed10d599d9628f40d9d1.js
finspector/labextension/static/269.40b3e09e815c15da5389.js
finspector/labextension/static/755.3a978543f6e4cc10f7a5.js
finspector/labextension/static/755.3a978543f6e4cc10f7a5.js.LICENSE.txt
finspector/labextension/static/796.14b3445f2f0c8ac027d3.js
finspector/labextension/static/909.2d4159888fc5a2124228.js
finspector/labextension/static/909.2d4159888fc5a2124228.js.LICENSE.txt
finspector/labextension/static/remoteEntry.f3c1a486f2cb31b5c37e.js
finspector/labextension/static/style.js
finspector/labextension/static/third-party-licenses.json
finspector/nbextension/extension.js
finspector/nbextension/index.js
finspector/nbextension/index.js.LICENSE.txt
finspector-0.1.0.data/data/etc/jupyter/nbconfig/notebook.d/finspector_js.json
finspector-0.1.0.data/data/share/jupyter/labextensions/finspector_js/install.json
finspector-0.1.0.data/data/share/jupyter/labextensions/finspector_js/package.json
finspector-0.1.0.data/data/share/jupyter/labextensions/finspector_js/static/154.77b0c11fea510ea9cf19.js
finspector-0.1.0.data/data/share/jupyter/labextensions/finspector_js/static/261.ed10d599d9628f40d9d1.js
finspector-0.1.0.data/data/share/jupyter/labextensions/finspector_js/static/269.40b3e09e815c15da5389.js
finspector-0.1.0.data/data/share/jupyter/labextensions/finspector_js/static/755.3a978543f6e4cc10f7a5.js
finspector-0.1.0.data/data/share/jupyter/labextensions/finspector_js/static/755.3a978543f6e4cc10f7a5.js.LICENSE.txt
finspector-0.1.0.data/data/share/jupyter/labextensions/finspector_js/static/796.14b3445f2f0c8ac027d3.js
finspector-0.1.0.data/data/share/jupyter/labextensions/finspector_js/static/909.2d4159888fc5a2124228.js
finspector-0.1.0.data/data/share/jupyter/labextensions/finspector_js/static/909.2d4159888fc5a2124228.js.LICENSE.txt
finspector-0.1.0.dist-info/LICENSE
finspector-0.1.0.dist-info/METADATA
finspector-0.1.0.dist-info/WHEEL
finspector-0.1.0.dist-info/top_level.txt
finspector-0.1.0.dist-info/RECORD
