Metadata-Version: 2.1
Name: finspector
Version: 0.1.0
Summary: A package that helps users explore fairness and bias of foundation models using pseudo-log-likelihood measures and interactive visualizations.
Home-page: https://github.com/IBM/finspector
Author: Bum Chul Kwon
Author-email: Bum Chul Kwon <bumchul.kwon@us.ibm.com>
License: MIT License
Project-URL: Homepage, https://github.com/IBM/finspector
Project-URL: Bug Tracker, https://github.com/IBM/finspector/issues
Keywords: ipython,widgets,Jupyter,JupyterLab,JupyterLab3
Classifier: Programming Language :: Python :: 3
Classifier: License :: OSI Approved :: MIT License
Classifier: Operating System :: OS Independent
Requires-Python: >=3.7
License-File: LICENSE
Requires-Dist: ipywidgets (<9,>=7.6.0)
